<annotation>
	<folder>vocal</folder>
	<filename>U.77423e6a-d331-11ec-87eb-d72bf436dde1.jpg</filename>
	<path>C:\workspaces\explore_sdd_sibi\collected\vocal\U.77423e6a-d331-11ec-87eb-d72bf436dde1.jpg</path>
	<source>
		<database>Unknown</database>
	</source>
	<size>
		<width>640</width>
		<height>480</height>
		<depth>3</depth>
	</size>
	<segmented>0</segmented>
	<object>
		<name>U</name>
		<pose>Unspecified</pose>
		<truncated>0</truncated>
		<difficult>0</difficult>
		<bndbox>
			<xmin>316</xmin>
			<ymin>129</ymin>
			<xmax>433</xmax>
			<ymax>332</ymax>
		</bndbox>
	</object>
</annotation>
